reponews/__init__.py
reponews/__main__.py
reponews/client.py
reponews/config.py
reponews/core.py
reponews/py.typed
reponews/qlobjs.py
reponews/qmanager.py
reponews/types.py
reponews/util.py
reponews-0.6.1.dist-info/METADATA
reponews-0.6.1.dist-info/WHEEL
reponews-0.6.1.dist-info/entry_points.txt
reponews-0.6.1.dist-info/licenses/LICENSE
reponews-0.6.1.dist-info/RECORD
