Metadata-Version: 2.4
Name: reponews
Version: 0.6.1
Summary: Send e-mails about new events on your GitHub repositories
Project-URL: Source Code, https://github.com/jwodder/reponews
Project-URL: Bug Tracker, https://github.com/jwodder/reponews/issues
Author-email: John Thorvald Wodder II <reponews@varonathe.org>
License-Expression: MIT
License-File: LICENSE
Keywords: GitHub,GitHub activity,GitHub issues,e-mail,notifications,pull requests
Classifier: Environment :: Console
Classifier: Intended Audience :: Information Technology
Classifier: Programming Language :: Python :: 3
Classifier: Programming Language :: Python :: 3 :: Only
Classifier: Programming Language :: Python :: 3.8
Classifier: Programming Language :: Python :: 3.9
Classifier: Programming Language :: Python :: 3.10
Classifier: Programming Language :: Python :: 3.11
Classifier: Programming Language :: Python :: 3.12
Classifier: Programming Language :: Python :: 3.13
Classifier: Programming Language :: Python :: Implementation :: CPython
Classifier: Programming Language :: Python :: Implementation :: PyPy
Classifier: Topic :: Communications :: Email
Classifier: Topic :: Software Development :: Bug Tracking
Classifier: Typing :: Typed
Requires-Python: >=3.8
Requires-Dist: click!=8.2.2,>=8.0
Requires-Dist: click-loglevel~=0.5
Requires-Dist: eletter~=0.2
Requires-Dist: ghrepo~=0.1
Requires-Dist: ghtoken~=0.1
Requires-Dist: mailbits~=0.2
Requires-Dist: outgoing~=0.6
Requires-Dist: platformdirs<5.0,>=3.0
Requires-Dist: pydantic~=2.0
Requires-Dist: python-dotenv<2.0,>=0.11
Requires-Dist: requests~=2.20
Requires-Dist: tomli<3.0,>=1.2; python_version < '3.11'
Requires-Dist: typing-extensions; python_version < '3.9'
